girder_dataflows/__init__.py
girder_dataflows/constants.py
girder_dataflows/lib/__init__.py
girder_dataflows/lib/dagster_workspace.py
girder_dataflows/lib/service.py
girder_dataflows/models/__init__.py
girder_dataflows/models/dataflow.py
girder_dataflows/models/spec.py
girder_dataflows/rest/__init__.py
girder_dataflows/rest/dataflow.py
girder_dataflows/rest/spec.py
girder_dataflows/web_client/dist/girder-plugin-dataflows.umd.cjs
girder_dataflows/web_client/dist/style.css
girder_dataflows-2.0.2.dist-info/licenses/LICENSE
girder_dataflows-2.0.2.dist-info/METADATA
girder_dataflows-2.0.2.dist-info/WHEEL
girder_dataflows-2.0.2.dist-info/entry_points.txt
girder_dataflows-2.0.2.dist-info/top_level.txt
girder_dataflows-2.0.2.dist-info/RECORD
